ichigo/__init__.py
ichigo/asr/__init__.py
ichigo/asr/transcriber.py
ichigo/asr/arch/__init__.py
ichigo/asr/arch/layers.py
ichigo/asr/arch/quantizer.py
ichigo/asr/arch/r2t.py
ichigo/asr/arch/s2r.py
ichigo/asr/config/__init__.py
ichigo/asr/config/ichigo-asr-2501-en-vi.yaml
ichigo/asr/config/ichigo-asr-2501-en.yaml
ichigo/asr/config/ichigo-asr-2501-vi.yaml
ichigo/asr/config/ichigo-asr-2502-en.yaml
ichigo/asr/config/whispervq-2405-en.yaml
ichigo/asr/config/.ipynb_checkpoints/ichigo-asr-2502-en-checkpoint.yaml
ichigo/llm/__init__.py
ichigo/tts/__init__.py
ichigo-0.0.14.dist-info/METADATA
ichigo-0.0.14.dist-info/WHEEL
ichigo-0.0.14.dist-info/top_level.txt
ichigo-0.0.14.dist-info/RECORD
