Metadata-Version: 2.2
Name: ichigo
Version: 0.0.14
Summary: Ichigo is an open, ongoing research experiment to extend a text-based LLM to have native listening ability. Think of it as an open data, open weight, on device Siri.
Author-email: Charles <charles@jan.ai>
License: Apache-2.0
Keywords: asr,llm,tts,ichigo
Requires-Python: >=3.10
Requires-Dist: huggingface_hub==0.26.2
Requires-Dist: openai_whisper==20240930
Requires-Dist: torch==2.5.1
Requires-Dist: torchaudio==2.5.1
Requires-Dist: vector_quantize_pytorch==1.6.22
Requires-Dist: transformers
Requires-Dist: build
Requires-Dist: twine
Requires-Dist: fastapi
Requires-Dist: whisperspeech
Requires-Dist: accelerate>=0.26.0
Requires-Dist: datasets
Requires-Dist: jiwer
